lsqfitgp/_Deriv.py
lsqfitgp/__init__.py
lsqfitgp/_array.py
lsqfitgp/_fastraniter.py
lsqfitgp/_fit.py
lsqfitgp/_patch_gvar.py
lsqfitgp/_patch_jax.py
lsqfitgp/_signature.py
lsqfitgp/_utils.py
lsqfitgp/_GP/__init__.py
lsqfitgp/_GP/_base.py
lsqfitgp/_GP/_compute.py
lsqfitgp/_GP/_elements.py
lsqfitgp/_GP/_gp.py
lsqfitgp/_GP/_processes.py
lsqfitgp/_Kernel/__init__.py
lsqfitgp/_Kernel/_alg.py
lsqfitgp/_Kernel/_crosskernel.py
lsqfitgp/_Kernel/_decorators.py
lsqfitgp/_Kernel/_isotropic.py
lsqfitgp/_Kernel/_kernel.py
lsqfitgp/_Kernel/_ops.py
lsqfitgp/_Kernel/_stationary.py
lsqfitgp/_Kernel/_util.py
lsqfitgp/_gvarext/__init__.py
lsqfitgp/_gvarext/_format.py
lsqfitgp/_gvarext/_jacobian.py
lsqfitgp/_gvarext/_tabulate.py
lsqfitgp/_gvarext/_ufunc.py
lsqfitgp/_jaxext/__init__.py
lsqfitgp/_jaxext/_batcher.py
lsqfitgp/_jaxext/_fasthash.py
lsqfitgp/_kernels/__init__.py
lsqfitgp/_kernels/_arma.py
lsqfitgp/_kernels/_bart.py
lsqfitgp/_kernels/_basic.py
lsqfitgp/_kernels/_celerite.py
lsqfitgp/_kernels/_matern.py
lsqfitgp/_kernels/_randomwalk.py
lsqfitgp/_kernels/_spectral.py
lsqfitgp/_kernels/_wendland.py
lsqfitgp/_kernels/_zeta.py
lsqfitgp/_linalg/__init__.py
lsqfitgp/_linalg/_decomp.py
lsqfitgp/_linalg/_pytree.py
lsqfitgp/_linalg/_seqalg.py
lsqfitgp/_linalg/_stdcplx.py
lsqfitgp/_linalg/_toeplitz.py
lsqfitgp/_special/__init__.py
lsqfitgp/_special/_bernoulli.py
lsqfitgp/_special/_bessel.py
lsqfitgp/_special/_exp.py
lsqfitgp/_special/_expint.py
lsqfitgp/_special/_gamma.py
lsqfitgp/_special/_sinc.py
lsqfitgp/_special/_taylor.py
lsqfitgp/_special/_zeta.py
lsqfitgp/bayestree/__init__.py
lsqfitgp/bayestree/_bart.py
lsqfitgp/bayestree/_bcf.py
lsqfitgp/copula/__init__.py
lsqfitgp/copula/_base.py
lsqfitgp/copula/_beta.py
lsqfitgp/copula/_copula.py
lsqfitgp/copula/_copulas.py
lsqfitgp/copula/_distr.py
lsqfitgp/copula/_gamma.py
lsqfitgp/copula/_makedict.py
lsqfitgp-0.21.1.dist-info/licenses/LICENSE
lsqfitgp-0.21.1.dist-info/METADATA
lsqfitgp-0.21.1.dist-info/WHEEL
lsqfitgp-0.21.1.dist-info/top_level.txt
lsqfitgp-0.21.1.dist-info/RECORD
