Metadata-Version: 2.4
Name: lsqfitgp
Version: 0.21.1
Summary: A general purpose Gaussian process regression module
Author-email: Giacomo Petrillo <info@giacomopetrillo.com>
Project-URL: Homepage, https://github.com/Gattocrucco/lsqfitgp
Project-URL: Bug Tracker, https://github.com/Gattocrucco/lsqfitgp/issues
Classifier: Programming Language :: Python :: 3
Classifier: License :: OSI Approved :: GNU General Public License v3 (GPLv3)
Classifier: Development Status :: 3 - Alpha
Classifier: Operating System :: MacOS
Classifier: Operating System :: POSIX :: Linux
Requires-Python: >=3.10
License-File: LICENSE
Requires-Dist: numpy>=1.24
Requires-Dist: scipy>=1.10
Requires-Dist: jax>=0.4.35
Requires-Dist: jaxlib>=0.4.35
Requires-Dist: gvar>=12.0
Provides-Extra: dev
Requires-Dist: numpy; extra == "dev"
Requires-Dist: scipy; extra == "dev"
Requires-Dist: matplotlib; extra == "dev"
Requires-Dist: gvar; extra == "dev"
Requires-Dist: lsqfit; extra == "dev"
Requires-Dist: jax; extra == "dev"
Requires-Dist: jaxlib; extra == "dev"
Requires-Dist: sphinx; extra == "dev"
Requires-Dist: myst-parser; extra == "dev"
Requires-Dist: numpydoc; extra == "dev"
Requires-Dist: pytest; extra == "dev"
Requires-Dist: coverage[toml]; extra == "dev"
Requires-Dist: twine; extra == "dev"
Requires-Dist: ipython; extra == "dev"
Requires-Dist: mpmath; extra == "dev"
Requires-Dist: pandas; extra == "dev"
Requires-Dist: polars[pyarrow]; extra == "dev"
Requires-Dist: build; extra == "dev"
Requires-Dist: statsmodels; extra == "dev"
Requires-Dist: tqdm; extra == "dev"
Requires-Dist: tabulate; extra == "dev"
Requires-Dist: appnope; extra == "dev"
Provides-Extra: tests
Requires-Dist: numpy; extra == "tests"
Requires-Dist: scipy; extra == "tests"
Requires-Dist: gvar; extra == "tests"
Requires-Dist: jax; extra == "tests"
Requires-Dist: jaxlib; extra == "tests"
Requires-Dist: pytest; extra == "tests"
Requires-Dist: coverage[toml]; extra == "tests"
Requires-Dist: mpmath; extra == "tests"
Requires-Dist: pandas; extra == "tests"
Requires-Dist: polars[pyarrow]; extra == "tests"
Requires-Dist: statsmodels; extra == "tests"
Provides-Extra: tests-old
Requires-Dist: numpy==1.24; extra == "tests-old"
Requires-Dist: scipy==1.10; extra == "tests-old"
Requires-Dist: gvar==12.0; extra == "tests-old"
Requires-Dist: jax==0.4.35; extra == "tests-old"
Requires-Dist: jaxlib==0.4.35; extra == "tests-old"
Requires-Dist: pytest; extra == "tests-old"
Requires-Dist: coverage[toml]; extra == "tests-old"
Requires-Dist: mpmath; extra == "tests-old"
Requires-Dist: pandas<1.5; extra == "tests-old"
Requires-Dist: polars==1.0.0; extra == "tests-old"
Requires-Dist: pyarrow==10.0.1; extra == "tests-old"
Requires-Dist: statsmodels; extra == "tests-old"
Provides-Extra: docs
Requires-Dist: numpy; extra == "docs"
Requires-Dist: scipy; extra == "docs"
Requires-Dist: matplotlib; extra == "docs"
Requires-Dist: gvar; extra == "docs"
Requires-Dist: lsqfit; extra == "docs"
Requires-Dist: jax; extra == "docs"
Requires-Dist: jaxlib; extra == "docs"
Requires-Dist: sphinx; extra == "docs"
Requires-Dist: myst-parser; extra == "docs"
Requires-Dist: numpydoc; extra == "docs"
Requires-Dist: coverage[toml]; extra == "docs"
Requires-Dist: polars; extra == "docs"
Requires-Dist: pandas; extra == "docs"
Requires-Dist: statsmodels; extra == "docs"
Requires-Dist: pyarrow; extra == "docs"
Requires-Dist: tqdm; extra == "docs"
Requires-Dist: tabulate; extra == "docs"
Dynamic: license-file
